zp_data/__init__.py
zp_data/config.py
zp_data/cyclist.py
zp_data/primes.py
zp_data/result.py
zp_data/signup.py
zp_data/team.py
zp_data/zp.py
zp_data-0.1.0.dist-info/LICENSE
zp_data-0.1.0.dist-info/METADATA
zp_data-0.1.0.dist-info/WHEEL
zp_data-0.1.0.dist-info/top_level.txt
zp_data-0.1.0.dist-info/RECORD
