Metadata-Version: 2.1
Name: zp_data
Version: 0.1.0
Summary: A package for fetching data from Zwiftpower
Home-page: https://github.com/puckdoug/zp_data
Author: Doug Morris
Author-email: "Doug Morris" <doug@mhost.com>
License-File: LICENSE
Requires-Dist: httpx >=0.27.0
Requires-Dist: beautifulsoup4 >=4.12.3
Requires-Dist: keyring >=25.2.0
Requires-Dist: lxml >=5.2.1
